[
    {
        
        "photoFile": "https://ks-insta-bucket.s3.amazonaws.com/image/mt26f8429d-e735-4ff5-b2b0-f41ba8b45534.jpeg",
        "photoAuthor": "ks"
    },
    {
        "photoFile": "https://ks-insta-bucket.s3.amazonaws.com/image/hnce2df9c5-62bb-45e0-bfef-4070cea989f8.webp",
        "photoAuthor": "ks"
    },
    {
        "photoFile": "https://ks-insta-bucket.s3.amazonaws.com/image/mt26f8429d-e735-4ff5-b2b0-f41ba8b45534.jpeg",
        "photoAuthor": "ks"
    },
    {
      
        "photoFile": "https://ks-insta-bucket.s3.amazonaws.com/image/mt538311d6-4571-4038-bbe6-e33000d3e5a0.jpg",
        "photoAuthor": "mt"
    },
    {      
        "photoFile": "https://ks-insta-bucket.s3.amazonaws.com/image/mt915a0d51-0a0e-4d89-8f28-04d6e7c2de51.jpeg",
        "photoAuthor": "mt"
    }
  ]
  
